easy_manage/__init__.py
easy_manage/__main__.py
easy_manage/main.py
easy_manage/protocol.py
easy_manage/protocols.py
easy_manage/chassis/__init__.py
easy_manage/chassis/abstract_chassis.py
easy_manage/chassis/chassis_switch.py
easy_manage/chassis/constants.py
easy_manage/chassis/ipmi_chassis.py
easy_manage/chassis/redfish_chassis.py
easy_manage/components/__init__.py
easy_manage/connectors/__init__.py
easy_manage/connectors/connector.py
easy_manage/connectors/connectors_switch.py
easy_manage/connectors/exceptions.py
easy_manage/connectors/exceptions_connector.py
easy_manage/connectors/ipmi_connector.py
easy_manage/connectors/redfish_connector.py
easy_manage/connectors/ssh_connector.py
easy_manage/controller/__init__.py
easy_manage/controller/controller.py
easy_manage/controller/controller_factory.py
easy_manage/exceptions/__init__.py
easy_manage/exceptions/exceptions.py
easy_manage/shells/__init__.py
easy_manage/shells/bash_shell.py
easy_manage/systems/__init__.py
easy_manage/systems/abstract_system.py
easy_manage/systems/ipmi_system.py
easy_manage/systems/redfish_system.py
easy_manage/systems/system_switch.py
easy_manage/tools/__init__.py
easy_manage/tools/protocol.py
easy_manage/tools/wrap_with_protocol.py
easy_manage/tools/ipmi/__init__.py
easy_manage/tools/ipmi/ipmi_backend.py
easy_manage/tools/ipmi/chassis/__init__.py
easy_manage/tools/ipmi/chassis/chassis_messages.py
easy_manage/tools/ipmi/reducers/__init__.py
easy_manage/tools/ipmi/reducers/chassis_reducer.py
easy_manage/tools/ipmi/reducers/filtering_functions.py
easy_manage/tools/ipmi/reducers/ipmi_reducer.py
easy_manage/tools/ipmi/reducers/parsing_functions.py
easy_manage/tools/ipmi/reducers/system_reducer.py
easy_manage/tools/ipmi/reducers/constants/__init__.py
easy_manage/tools/ipmi/reducers/constants/exceptions.py
easy_manage/tools/ipmi/reducers/constants/paths.py
easy_manage/tools/ipmi/reducers/utils/__init__.py
easy_manage/tools/ipmi/reducers/utils/misc.py
easy_manage-0.0.1.dist-info/LICENSE
easy_manage-0.0.1.dist-info/METADATA
easy_manage-0.0.1.dist-info/WHEEL
easy_manage-0.0.1.dist-info/dependency_links.txt
easy_manage-0.0.1.dist-info/entry_points.txt
easy_manage-0.0.1.dist-info/top_level.txt
easy_manage-0.0.1.dist-info/RECORD
