Metadata-Version: 2.1
Name: easy-manage
Version: 0.0.1
Summary: Managing server infrastructure easily
Home-page: https://github.com/wojtekwanczyk/easy_manage
Author: Borkowski Szymus, Rejowski Tomus, Wanczyk Wojtek
Author-email: borkowskiszymon28@gmail.com, tomekgsd@gmail.com, wojtekwanczyk@gmail.com
License: UNKNOWN
Platform: UNKNOWN
Classifier: Programming Language :: Python :: 3
Classifier: License :: OSI Approved :: GNU General Public License v3 (GPLv3)
Classifier: Operating System :: OS Independent
Requires-Dist: redfish (>=2.1.0)
Requires-Dist: cryptography (>=2.7)
Requires-Dist: python-ipmi
Requires-Dist: paramiko (>=2.6.0)
Requires-Dist: inflection (>=0.3.1)
